[
  {
    "ticker": "BTC-USD",
    "close": 63864.39,
    "previousClose": null,
    "open": null,
    "high": null,
    "low": null,
    "volume": 26139967488,
    "timestamp": "2026-07-10T18:35:02.527710+00:00",
    "source": "yahoo"
  },
  {
    "ticker": "ETH-USD",
    "close": 1789.37,
    "previousClose": null,
    "open": null,
    "high": null,
    "low": null,
    "volume": 9402975232,
    "timestamp": "2026-07-10T18:35:03.273534+00:00",
    "source": "yahoo"
  },
  {
    "ticker": "SOL-USD",
    "close": 77.7,
    "previousClose": null,
    "open": null,
    "high": null,
    "low": null,
    "volume": 2050672896,
    "timestamp": "2026-07-10T18:35:03.985318+00:00",
    "source": "yahoo"
  },
  {
    "ticker": "BNB-USD",
    "close": 576.45,
    "previousClose": null,
    "open": null,
    "high": null,
    "low": null,
    "volume": 1044405376,
    "timestamp": "2026-07-10T18:35:04.696291+00:00",
    "source": "yahoo"
  },
  {
    "ticker": "DOGE-USD",
    "close": 0.07388,
    "previousClose": null,
    "open": null,
    "high": null,
    "low": null,
    "volume": 497332320,
    "timestamp": "2026-07-10T18:35:05.415281+00:00",
    "source": "yahoo"
  },
  {
    "ticker": "AAPL",
    "close": 314.8,
    "previousClose": null,
    "open": null,
    "high": null,
    "low": null,
    "volume": 16511630,
    "timestamp": "2026-07-10T18:35:06.090144+00:00",
    "source": "yahoo"
  },
  {
    "ticker": "MSFT",
    "close": 385.295,
    "previousClose": null,
    "open": null,
    "high": null,
    "low": null,
    "volume": 15357762,
    "timestamp": "2026-07-10T18:35:06.739862+00:00",
    "source": "yahoo"
  },
  {
    "ticker": "GOOGL",
    "close": 355.42,
    "previousClose": null,
    "open": null,
    "high": null,
    "low": null,
    "volume": 10878797,
    "timestamp": "2026-07-10T18:35:07.410286+00:00",
    "source": "yahoo"
  },
  {
    "ticker": "AMZN",
    "close": 245.71,
    "previousClose": null,
    "open": null,
    "high": null,
    "low": null,
    "volume": 19658415,
    "timestamp": "2026-07-10T18:35:08.177869+00:00",
    "source": "yahoo"
  },
  {
    "ticker": "TSLA",
    "close": 408.895,
    "previousClose": null,
    "open": null,
    "high": null,
    "low": null,
    "volume": 25649309,
    "timestamp": "2026-07-10T18:35:08.842269+00:00",
    "source": "yahoo"
  },
  {
    "ticker": "NVDA",
    "close": 210.35,
    "previousClose": null,
    "open": null,
    "high": null,
    "low": null,
    "volume": 104295319,
    "timestamp": "2026-07-10T18:35:09.497072+00:00",
    "source": "yahoo"
  },
  {
    "ticker": "META",
    "close": 668.155,
    "previousClose": null,
    "open": null,
    "high": null,
    "low": null,
    "volume": 30304264,
    "timestamp": "2026-07-10T18:35:10.156635+00:00",
    "source": "yahoo"
  },
  {
    "ticker": "JPM",
    "close": 337.095,
    "previousClose": null,
    "open": null,
    "high": null,
    "low": null,
    "volume": 2486022,
    "timestamp": "2026-07-10T18:35:10.948274+00:00",
    "source": "yahoo"
  },
  {
    "ticker": "COST",
    "close": 914.75,
    "previousClose": null,
    "open": null,
    "high": null,
    "low": null,
    "volume": 1134799,
    "timestamp": "2026-07-10T18:35:11.718048+00:00",
    "source": "yahoo"
  },
  {
    "ticker": "LLY",
    "close": 1187.245,
    "previousClose": null,
    "open": null,
    "high": null,
    "low": null,
    "volume": 1254391,
    "timestamp": "2026-07-10T18:35:12.498498+00:00",
    "source": "yahoo"
  },
  {
    "ticker": "SPCX",
    "close": 148.82,
    "previousClose": null,
    "open": null,
    "high": null,
    "low": null,
    "volume": 28213494,
    "timestamp": "2026-07-10T18:35:13.242516+00:00",
    "source": "yahoo"
  },
  {
    "ticker": "SPY",
    "close": 754.48,
    "previousClose": null,
    "open": null,
    "high": null,
    "low": null,
    "volume": 23193191,
    "timestamp": "2026-07-10T18:35:13.896461+00:00",
    "source": "yahoo"
  },
  {
    "ticker": "QQQ",
    "close": 725.855,
    "previousClose": null,
    "open": null,
    "high": null,
    "low": null,
    "volume": 20574238,
    "timestamp": "2026-07-10T18:35:14.617897+00:00",
    "source": "yahoo"
  },
  {
    "ticker": "DIA",
    "close": 525.99,
    "previousClose": null,
    "open": null,
    "high": null,
    "low": null,
    "volume": 2265961,
    "timestamp": "2026-07-10T18:35:15.367249+00:00",
    "source": "yahoo"
  },
  {
    "ticker": "IWM",
    "close": 296.17,
    "previousClose": null,
    "open": null,
    "high": null,
    "low": null,
    "volume": 10999634,
    "timestamp": "2026-07-10T18:35:16.103562+00:00",
    "source": "yahoo"
  }
]