[
  {
    "ticker": "BTC-USD",
    "close": 63993.16,
    "previousClose": null,
    "open": null,
    "high": null,
    "low": null,
    "volume": 26729650176,
    "timestamp": "2026-07-10T17:05:01.703138+00:00",
    "source": "yahoo"
  },
  {
    "ticker": "ETH-USD",
    "close": 1793.04,
    "previousClose": null,
    "open": null,
    "high": null,
    "low": null,
    "volume": 9395244032,
    "timestamp": "2026-07-10T17:05:02.373493+00:00",
    "source": "yahoo"
  },
  {
    "ticker": "SOL-USD",
    "close": 78.09,
    "previousClose": null,
    "open": null,
    "high": null,
    "low": null,
    "volume": 2019497344,
    "timestamp": "2026-07-10T17:05:03.079744+00:00",
    "source": "yahoo"
  },
  {
    "ticker": "BNB-USD",
    "close": 576.13,
    "previousClose": null,
    "open": null,
    "high": null,
    "low": null,
    "volume": 1043361344,
    "timestamp": "2026-07-10T17:05:03.758048+00:00",
    "source": "yahoo"
  },
  {
    "ticker": "DOGE-USD",
    "close": 0.07422,
    "previousClose": null,
    "open": null,
    "high": null,
    "low": null,
    "volume": 499527296,
    "timestamp": "2026-07-10T17:05:04.468829+00:00",
    "source": "yahoo"
  },
  {
    "ticker": "AAPL",
    "close": 314.56,
    "previousClose": null,
    "open": null,
    "high": null,
    "low": null,
    "volume": 14139446,
    "timestamp": "2026-07-10T17:05:05.165261+00:00",
    "source": "yahoo"
  },
  {
    "ticker": "MSFT",
    "close": 385.721,
    "previousClose": null,
    "open": null,
    "high": null,
    "low": null,
    "volume": 12171017,
    "timestamp": "2026-07-10T17:05:05.884701+00:00",
    "source": "yahoo"
  },
  {
    "ticker": "GOOGL",
    "close": 354.96,
    "previousClose": null,
    "open": null,
    "high": null,
    "low": null,
    "volume": 8774845,
    "timestamp": "2026-07-10T17:05:06.539878+00:00",
    "source": "yahoo"
  },
  {
    "ticker": "AMZN",
    "close": 245.625,
    "previousClose": null,
    "open": null,
    "high": null,
    "low": null,
    "volume": 15224142,
    "timestamp": "2026-07-10T17:05:07.186320+00:00",
    "source": "yahoo"
  },
  {
    "ticker": "TSLA",
    "close": 411.75,
    "previousClose": null,
    "open": null,
    "high": null,
    "low": null,
    "volume": 20364944,
    "timestamp": "2026-07-10T17:05:07.865513+00:00",
    "source": "yahoo"
  },
  {
    "ticker": "NVDA",
    "close": 209.76,
    "previousClose": null,
    "open": null,
    "high": null,
    "low": null,
    "volume": 85181895,
    "timestamp": "2026-07-10T17:05:08.663846+00:00",
    "source": "yahoo"
  },
  {
    "ticker": "META",
    "close": 665.412,
    "previousClose": null,
    "open": null,
    "high": null,
    "low": null,
    "volume": 26477112,
    "timestamp": "2026-07-10T17:05:09.373844+00:00",
    "source": "yahoo"
  },
  {
    "ticker": "JPM",
    "close": 336.67,
    "previousClose": null,
    "open": null,
    "high": null,
    "low": null,
    "volume": 1754428,
    "timestamp": "2026-07-10T17:05:10.127730+00:00",
    "source": "yahoo"
  },
  {
    "ticker": "COST",
    "close": 914.86,
    "previousClose": null,
    "open": null,
    "high": null,
    "low": null,
    "volume": 970507,
    "timestamp": "2026-07-10T17:05:10.835200+00:00",
    "source": "yahoo"
  },
  {
    "ticker": "LLY",
    "close": 1180.875,
    "previousClose": null,
    "open": null,
    "high": null,
    "low": null,
    "volume": 1033102,
    "timestamp": "2026-07-10T17:05:11.612798+00:00",
    "source": "yahoo"
  },
  {
    "ticker": "SPCX",
    "close": 148.7,
    "previousClose": null,
    "open": null,
    "high": null,
    "low": null,
    "volume": 25191971,
    "timestamp": "2026-07-10T17:05:12.309642+00:00",
    "source": "yahoo"
  },
  {
    "ticker": "SPY",
    "close": 753.7,
    "previousClose": null,
    "open": null,
    "high": null,
    "low": null,
    "volume": 17040800,
    "timestamp": "2026-07-10T17:05:13.062916+00:00",
    "source": "yahoo"
  },
  {
    "ticker": "QQQ",
    "close": 724.71,
    "previousClose": null,
    "open": null,
    "high": null,
    "low": null,
    "volume": 16501561,
    "timestamp": "2026-07-10T17:05:13.753333+00:00",
    "source": "yahoo"
  },
  {
    "ticker": "DIA",
    "close": 525.55,
    "previousClose": null,
    "open": null,
    "high": null,
    "low": null,
    "volume": 1923847,
    "timestamp": "2026-07-10T17:05:14.548609+00:00",
    "source": "yahoo"
  },
  {
    "ticker": "IWM",
    "close": 295.73,
    "previousClose": null,
    "open": null,
    "high": null,
    "low": null,
    "volume": 9230718,
    "timestamp": "2026-07-10T17:05:15.323474+00:00",
    "source": "yahoo"
  }
]